aqequil-1.0.0.dist-info/WHEEL
aqequil-1.0.0.dist-info/top_level.txt
aqequil-1.0.0.dist-info/METADATA
aqequil-1.0.0.dist-info/RECORD
aqequil-1.0.0.dist-info/licenses/LICENSE.txt
aqequil/dissrxn_balancer.py
aqequil/preprocess_for_EQ3.py
aqequil/output_3o_mine.py
aqequil/_HKF_cgl.py
aqequil/check_TP_grid.py
aqequil/formula_parser.py
aqequil/MassTransfer.py
aqequil/half_cell_reactions.csv
aqequil/AqSpeciation.py
aqequil/create_data0.py
aqequil/dissrxn_generator.py
aqequil/process_dissrxns.py
aqequil/speciation_groups_WORM.txt
aqequil/data0.min
aqequil/__init__.py
aqequil/fill_data0_header.py
aqequil/redox_suppression.py
aqequil/eq3_6_src/__init__.py
aqequil/eq3_6_src/Makefile
aqequil/eq3_6_src/include/xcon3/x3op7.h
aqequil/eq3_6_src/include/xcon3/x3op7d.h
aqequil/eq3_6_src/include/xcon6/x6sbsp.h
aqequil/eq3_6_src/include/xcon6/x6op7d.h
aqequil/eq3_6_src/include/xcon6/x6op7.h
aqequil/eq3_6_src/include/eqlib/eqldv.h
aqequil/eq3_6_src/include/eqlib/eqlj8d.h
aqequil/eq3_6_src/include/eqlib/eqlk8.h
aqequil/eq3_6_src/include/eqlib/eqldef.h
aqequil/eq3_6_src/include/eqlib/eqlo8.h
aqequil/eq3_6_src/include/eqlib/eqlpar.h
aqequil/eq3_6_src/include/eqlib/eqltf2.h
aqequil/eq3_6_src/include/eqlib/eql1s.h
aqequil/eq3_6_src/include/eqlib/eqlj8.h
aqequil/eq3_6_src/include/eqlib/eqlge.h
aqequil/eq3_6_src/include/eqlib/eqlwdd.h
aqequil/eq3_6_src/include/eqlib/eql1sd.h
aqequil/eq3_6_src/include/eqlib/eqlo8d.h
aqequil/eq3_6_src/include/eqlib/eqlk8d.h
aqequil/eq3_6_src/include/eqlib/eqltf1.h
aqequil/eq3_6_src/include/eqlib/eqlwd.h
aqequil/eq3_6_src/src/Makefile.exe.in
aqequil/eq3_6_src/src/Makefile.lib.in
aqequil/eq3_6_src/src/eqlibg/Makefile
aqequil/eq3_6_src/src/eqlibg/obj/ptzchk.o
aqequil/eq3_6_src/src/eqlibg/obj/gselm.o
aqequil/eq3_6_src/src/eqlibg/obj/wterm.o
aqequil/eq3_6_src/src/eqlibg/obj/gesum.o
aqequil/eq3_6_src/src/eqlibg/obj/cfjest.o
aqequil/eq3_6_src/src/eqlibg/obj/ghj0.o
aqequil/eq3_6_src/src/eqlibg/obj/gmsum.o
aqequil/eq3_6_src/src/eqlibg/obj/aaaelg.o
aqequil/eq3_6_src/src/eqlibg/obj/gpj0.o
aqequil/eq3_6_src/src/eqlibg/obj/cfxist.o
aqequil/eq3_6_src/src/eqlibg/obj/gslam.o
