Metadata-Version: 2.4
Name: aqequil
Version: 1.0.0
Summary: Python tools for aqueous chemical speciation.
Author-email: Grayson Boyer <gmboyer@asu.edu>
License: MIT
Project-URL: Homepage, https://github.com/worm-portal/aqequil
Classifier: Programming Language :: Python :: 3
Classifier: License :: OSI Approved :: MIT License
Classifier: Operating System :: OS Independent
Requires-Python: >=3.10
License-File: LICENSE.txt
Requires-Dist: pandas
Requires-Dist: numpy
Requires-Dist: matplotlib
Requires-Dist: plotly
Requires-Dist: ipython
Requires-Dist: chemparse
Requires-Dist: dill
Requires-Dist: periodictable
Requires-Dist: natsort
Requires-Dist: roman
Requires-Dist: ipywidgets
Requires-Dist: wormutils
Requires-Dist: pychnosz
Dynamic: license-file
